LICENSE
README.md
setup.py
fortnitepy/__init__.py
fortnitepy/auth.py
fortnitepy/client.py
fortnitepy/enums.py
fortnitepy/errors.py
fortnitepy/friend.py
fortnitepy/http.py
fortnitepy/kairos.py
fortnitepy/message.py
fortnitepy/news.py
fortnitepy/party.py
fortnitepy/playlist.py
fortnitepy/presence.py
fortnitepy/stats.py
fortnitepy/store.py
fortnitepy/typedefs.py
fortnitepy/user.py
fortnitepy/utils.py
fortnitepy/xmpp.py
fortnitepy.egg-info/PKG-INFO
fortnitepy.egg-info/SOURCES.txt
fortnitepy.egg-info/dependency_links.txt
fortnitepy.egg-info/requires.txt
fortnitepy.egg-info/top_level.txt
fortnitepy/ext/commands/__init__.py
fortnitepy/ext/commands/_types.py
fortnitepy/ext/commands/bot.py
fortnitepy/ext/commands/cog.py
fortnitepy/ext/commands/context.py
fortnitepy/ext/commands/converter.py
fortnitepy/ext/commands/cooldown.py
fortnitepy/ext/commands/core.py
fortnitepy/ext/commands/errors.py
fortnitepy/ext/commands/help.py
fortnitepy/ext/commands/typedefs.py
fortnitepy/ext/commands/view.py