Metadata-Version: 2.1
Name: fortnitepy
Version: 3.6.8
Summary: Library for interacting with fortnite services
Home-page: https://github.com/Terbau/fortnitepy
Author: Terbau
License: MIT
Project-URL: Documentation, https://fortnitepy.readthedocs.io/en/latest/
Project-URL: Issue tracker, https://github.com/Terbau/fortnitepy/issues
Classifier: License :: OSI Approved :: MIT License
Classifier: Intended Audience :: Developers
Classifier: Natural Language :: English
Classifier: Operating System :: OS Independent
Classifier: Programming Language :: Python :: 3.5
Classifier: Programming Language :: Python :: 3.6
Classifier: Programming Language :: Python :: 3.7
Classifier: Programming Language :: Python :: 3.8
Classifier: Programming Language :: Python :: 3.9
Classifier: Topic :: Internet
Classifier: Topic :: Software Development :: Libraries
Classifier: Topic :: Software Development :: Libraries :: Python Modules
Classifier: Topic :: Utilities
Requires-Python: >=3.5.3
Provides-Extra: docs
License-File: LICENSE
